gematria_engine/__init__.py
gematria_engine/gematria.py
gematria_engine/maps.py
gematria_engine/paleo.py
gematria_engine/systems/__init__.py
gematria_engine/systems/atbash.py
gematria_engine/systems/gadol.py
gematria_engine/systems/init.py
gematria_engine/systems/katan.py
gematria_engine/systems/ordinal.py
gematria_engine/systems/standard.py
gematria_engine-0.1.0.dist-info/licenses/LICENSE.txt
gematria_engine-0.1.0.dist-info/.gitignore
gematria_engine-0.1.0.dist-info/METADATA
gematria_engine-0.1.0.dist-info/WHEEL
gematria_engine-0.1.0.dist-info/top_level.txt
gematria_engine-0.1.0.dist-info/RECORD
