Metadata-Version: 2.4
Name: gematria-engine
Version: 0.1.0
Summary: A clean, minimal Hebrew gematria engine for Python.
Author: Matthew
Project-URL: Homepage, https://pypi.org/project/gematria-engine/
Keywords: gematria,hebrew,numerology,bible code
Classifier: Programming Language :: Python :: 3
Classifier: License :: OSI Approved :: MIT License
Classifier: Operating System :: OS Independent
Classifier: Topic :: Text Processing
Classifier: Topic :: Scientific/Engineering :: Information Analysis
Requires-Python: >=3.8
License-File: LICENSE.txt
Dynamic: license-file
